vesta/__init__.py
vesta/db/UNIAUTH.sql
vesta/db/db_service.py
vesta/emptyProject/.gitignore
vesta/emptyProject/.gitlab-ci.yml
vesta/emptyProject/CONTRIBUTING.md
vesta/emptyProject/LICENSE.md
vesta/emptyProject/README.md
vesta/emptyProject/install.sh
vesta/emptyProject/requirements.txt
vesta/emptyProject/server_static.ini
vesta/emptyProject/server_static.py
vesta/emptyProject/server_static_orm.ini
vesta/emptyProject/server_static_orm.py
vesta/emptyProject/server_vesta.ini
vesta/emptyProject/server_vesta.py
vesta/emptyProject/server_vesta_ws.ini
vesta/emptyProject/server_vesta_ws.py
vesta/emptyProject/crons/exemple.py
vesta/emptyProject/db/schema.sql
vesta/emptyProject/mailing/mailReset.html
vesta/emptyProject/mailing/mailVerif.html
vesta/emptyProject/misc/nginx_local
vesta/emptyProject/misc/nginx_prod
vesta/emptyProject/misc/nginx_prod_ws
vesta/emptyProject/misc/vesta.service
vesta/emptyProject/static/main.html
vesta/emptyProject/static/main.mjs
vesta/emptyProject/static/mobileUiManifest.mjs
vesta/emptyProject/static/style.css
vesta/emptyProject/static/framework/global.mjs
vesta/emptyProject/static/framework/navigation.mjs
vesta/emptyProject/static/framework/templating.mjs
vesta/emptyProject/static/framework/vesta.mjs
vesta/emptyProject/static/framework/websockets.mjs
vesta/emptyProject/static/home/auth.css
vesta/emptyProject/static/home/auth.html
vesta/emptyProject/static/home/auth.js
vesta/emptyProject/static/home/reset.html
vesta/emptyProject/static/home/verif.html
vesta/emptyProject/static/markdown/markdown.mjs
vesta/emptyProject/static/markdown/utils.mjs
vesta/emptyProject/static/translations/en.mjs
vesta/emptyProject/static/translations/fr.mjs
vesta/emptyProject/static/translations/translation.mjs
vesta/emptyProject/static/ws/onMessage.mjs
vesta/emptyProject/tests/example/foo.py
vesta/http/baseServer.py
vesta/http/error.py
vesta/http/redirect.py
vesta/http/response.py
vesta/mailing/mailing_service.py
vesta/scripts/cli.py
vesta/scripts/initDB.py
vesta_web-1.2.1.dist-info/METADATA
vesta_web-1.2.1.dist-info/WHEEL
vesta_web-1.2.1.dist-info/entry_points.txt
vesta_web-1.2.1.dist-info/licenses/LICENSE.md
vesta_web-1.2.1.dist-info/RECORD
