Metadata-Version: 2.4
Name: vesta-web
Version: 1.2.1
Summary: An extensive web framework adding every feature needed for Carbonlab
Project-URL: Homepage, https://gitlab.com/Louciole/vesta
Project-URL: Issues, https://gitlab.com/Louciole/vesta/-/issues
Author-email: Lou !  <lou@carbonlab.dev>
License: # Copyright (C) Carbonlab - All Rights Reserved
License-File: LICENSE.md
Classifier: Operating System :: OS Independent
Classifier: Programming Language :: Python :: 3
Classifier: Topic :: Internet :: WWW/HTTP
Requires-Python: >=3.8
Requires-Dist: bcrypt
Requires-Dist: colorama
Requires-Dist: configparser
Requires-Dist: dkimpy
Requires-Dist: fastwsgi
Requires-Dist: multipart
Requires-Dist: psycopg
Requires-Dist: pyjwt
Requires-Dist: setuptools
Requires-Dist: websockets
